<error>
<domain>STATIC_C</domain>
<lang>C++</lang>
<checker>NO_EFFECT</checker>
<type>no_effect</type>
<subtype>extra_comma</subtype>
<file>D:/Microsoft Visual Studio 9.0/VC/include/xlocale</file>
<merge_with_lowercase_file>true</merge_with_lowercase_file>
<function>_ZNKSt5ctypeIwE11_Do_widen_sEPKcS2_Pwj</function>
<score>100</score>
<ordered>false</ordered>
<event>
<main>true</main>
<tag>extra_comma</tag>
<description>{CovLStrv2{{t{Part {0} of statement {1} has no effect due to the comma.}{{code{&quot;_Dest_size &gt;= (size_t)(_Last - _First)&quot;}}}{{code{&quot;_Dest_size &gt;= (size_t)(_Last - _First)&quot; , 0}}}}}}</description>
<line>2137</line>
</event>
<extra></extra>
<subcategory>extra_comma</subcategory>
</error>
<error>
<domain>STATIC_C</domain>
<lang>C++</lang>
<checker>NO_EFFECT</checker>
<type>no_effect</type>
<subtype>extra_comma</subtype>
<file>D:/Microsoft Visual Studio 9.0/VC/include/xlocale</file>
<merge_with_lowercase_file>true</merge_with_lowercase_file>
<function>_ZNKSt5ctypeIwE12_Do_narrow_sEPKwS2_cPcj</function>
<score>100</score>
<ordered>false</ordered>
<event>
<main>true</main>
<tag>extra_comma</tag>
<description>{CovLStrv2{{t{Part {0} of statement {1} has no effect due to the comma.}{{code{&quot;_Dest_size &gt;= (size_t)(_Last - _First)&quot;}}}{{code{&quot;_Dest_size &gt;= (size_t)(_Last - _First)&quot; , 0}}}}}}</description>
<line>2172</line>
</event>
<extra></extra>
<subcategory>extra_comma</subcategory>
</error>
<error>
<domain>STATIC_C</domain>
<lang>C++</lang>
<checker>NO_EFFECT</checker>
<type>no_effect</type>
<subtype>extra_comma</subtype>
<file>D:/Microsoft Visual Studio 9.0/VC/include/xlocale</file>
<merge_with_lowercase_file>true</merge_with_lowercase_file>
<function>_ZNKSt5ctypeIcE11_Do_widen_sEPKcS2_Pcj</function>
<score>100</score>
<ordered>false</ordered>
<event>
<main>true</main>
<tag>extra_comma</tag>
<description>{CovLStrv2{{t{Part {0} of statement {1} has no effect due to the comma.}{{code{&quot;_Dest_size &gt;= (size_t)(_Last - _First)&quot;}}}{{code{&quot;_Dest_size &gt;= (size_t)(_Last - _First)&quot; , 0}}}}}}</description>
<line>1865</line>
</event>
<extra></extra>
<subcategory>extra_comma</subcategory>
</error>
<error>
<domain>STATIC_C</domain>
<lang>C++</lang>
<checker>NO_EFFECT</checker>
<type>no_effect</type>
<subtype>extra_comma</subtype>
<file>D:/Microsoft Visual Studio 9.0/VC/include/xlocale</file>
<merge_with_lowercase_file>true</merge_with_lowercase_file>
<function>_ZNKSt5ctypeIcE12_Do_narrow_sEPKcS2_cPcj</function>
<score>100</score>
<ordered>false</ordered>
<event>
<main>true</main>
<tag>extra_comma</tag>
<description>{CovLStrv2{{t{Part {0} of statement {1} has no effect due to the comma.}{{code{&quot;_Dest_size &gt;= (size_t)(_Last - _First)&quot;}}}{{code{&quot;_Dest_size &gt;= (size_t)(_Last - _First)&quot; , 0}}}}}}</description>
<line>1890</line>
</event>
<extra></extra>
<subcategory>extra_comma</subcategory>
</error>
<error>
<domain>STATIC_C</domain>
<lang>C++</lang>
<checker>NO_EFFECT</checker>
<type>no_effect</type>
<subtype>extra_comma</subtype>
<file>D:/Microsoft Visual Studio 9.0/VC/include/xlocale</file>
<merge_with_lowercase_file>true</merge_with_lowercase_file>
<function>_ZNKSt5ctypeItE11_Do_widen_sEPKcS2_Ptj</function>
<score>100</score>
<ordered>false</ordered>
<event>
<main>true</main>
<tag>extra_comma</tag>
<description>{CovLStrv2{{t{Part {0} of statement {1} has no effect due to the comma.}{{code{&quot;_Dest_size &gt;= (size_t)(_Last - _First)&quot;}}}{{code{&quot;_Dest_size &gt;= (size_t)(_Last - _First)&quot; , 0}}}}}}</description>
<line>2420</line>
</event>
<extra></extra>
<subcategory>extra_comma</subcategory>
</error>
<error>
<domain>STATIC_C</domain>
<lang>C++</lang>
<checker>NO_EFFECT</checker>
<type>no_effect</type>
<subtype>extra_comma</subtype>
<file>D:/Microsoft Visual Studio 9.0/VC/include/xlocale</file>
<merge_with_lowercase_file>true</merge_with_lowercase_file>
<function>_ZNKSt5ctypeItE12_Do_narrow_sEPKtS2_cPcj</function>
<score>100</score>
<ordered>false</ordered>
<event>
<main>true</main>
<tag>extra_comma</tag>
<description>{CovLStrv2{{t{Part {0} of statement {1} has no effect due to the comma.}{{code{&quot;_Dest_size &gt;= (size_t)(_Last - _First)&quot;}}}{{code{&quot;_Dest_size &gt;= (size_t)(_Last - _First)&quot; , 0}}}}}}</description>
<line>2454</line>
</event>
<extra></extra>
<subcategory>extra_comma</subcategory>
</error>
